Metadata-Version: 1.0
Name: encryptionSSS
Version: 0.0
Summary: encryptionSSS
Home-page: UNKNOWN
Author: UNKNOWN
Author-email: max.taran.210@mail.ru
License: UNKNOWN
Platform: UNKNOWN
